{
"skeleton": { "hash": "MzQKgJkyZ7JIqrdRHx0AQaJlw+0", "spine": "3.8.75", "images": "C:/Users/PC/Documents/88 Group Projects/build/slot_spine/src/assets/slot/images/trolly/", "audio": "C:\\Users\\PC\\Documents\\88 Group Projects\\build\\slot_spine\\src\\assets\\slot\\images" },
"bones": [
	{ "name": "root" }
],
"slots": [
	{ "name": "Layer 1", "bone": "root", "attachment": "Layer 1" }
],
"skins": [
	{
		"name": "no_blur",
		"attachments": {
			"Layer 1": {
				"Layer 1": { "x": -1.5, "y": 116, "width": 291, "height": 240 }
			}
		}
	},
	{
		"name": "blur",
		"attachments": {
			"Layer 1": {
				"Layer 1": { "name": "blur", "x": -1.5, "y": 116, "width": 291, "height": 240 }
			}
		}
	}
],
"animations": {
	"animation": {
		"bones": {
			"root": {
				"scale": [
					{},
					{ "time": 0.3333, "x": 1.196, "y": 1.196 },
					{ "time": 0.6667 }
				]
			}
		}
	}
}
}